smem/__init__.py
smem/smem.py
smem-1.0.1.dist-info/METADATA
smem-1.0.1.dist-info/WHEEL
smem-1.0.1.dist-info/licenses/LICENSE
smem-1.0.1.dist-info/RECORD
