Metadata-Version: 2.3
Name: smem
Version: 1.0.1
Summary: A Python library that is used to handle interprocess communication platform independently in Python.
Project-URL: Homepage, https://github.com/hlpdev/SMem
Project-URL: Issues, https://github.com/hlpdev/SMem/issues
Author-email: Hunter Pollock <hunter@hnt8.net>
Classifier: License :: OSI Approved :: MIT License
Classifier: Operating System :: OS Independent
Classifier: Programming Language :: Python :: 3
Requires-Python: >=3.8
